lightning_action/__init__.py
lightning_action/api/__init__.py
lightning_action/api/model.py
lightning_action/cli/__init__.py
lightning_action/cli/commands/__init__.py
lightning_action/cli/commands/predict.py
lightning_action/cli/commands/train.py
lightning_action/cli/formatting.py
lightning_action/cli/main.py
lightning_action/cli/types.py
lightning_action/data/__init__.py
lightning_action/data/datamodule.py
lightning_action/data/datasets.py
lightning_action/data/transforms.py
lightning_action/data/utils.py
lightning_action/eval.py
lightning_action/models/__init__.py
lightning_action/models/backbones/__init__.py
lightning_action/models/backbones/rnn.py
lightning_action/models/backbones/tcn.py
lightning_action/models/backbones/temporalmlp.py
lightning_action/models/segmenter.py
lightning_action/train.py
lightning_action-0.2.4.dist-info/METADATA
lightning_action-0.2.4.dist-info/WHEEL
lightning_action-0.2.4.dist-info/entry_points.txt
lightning_action-0.2.4.dist-info/licenses/LICENSE
lightning_action-0.2.4.dist-info/RECORD
