Metadata-Version: 2.4
Name: lightning-action
Version: 0.2.4
Summary: Action segmentation framework built with PyTorch Lightning
License-Expression: MIT
License-File: LICENSE
Keywords: machine learning,deep learning,action segmentation,computer vision
Author: Matt Whiteway
Requires-Python: >=3.10
Classifier: Development Status :: 2 - Pre-Alpha
Classifier: Intended Audience :: Science/Research
Classifier: License :: OSI Approved :: MIT License
Classifier: Programming Language :: Python :: 3
Classifier: Programming Language :: Python :: 3.10
Classifier: Programming Language :: Python :: 3.11
Classifier: Programming Language :: Python :: 3.12
Classifier: Topic :: Scientific/Engineering :: Artificial Intelligence
Classifier: Topic :: Scientific/Engineering :: Image Processing
Provides-Extra: dev
Requires-Dist: flake8-pyproject ; extra == "dev"
Requires-Dist: isort ; extra == "dev"
Requires-Dist: jaxtyping
Requires-Dist: lightning
Requires-Dist: numpy (>=2.0.0)
Requires-Dist: pandas
Requires-Dist: pytest ; extra == "dev"
Requires-Dist: pytest-html ; extra == "dev"
Requires-Dist: pyyaml
Requires-Dist: requests ; extra == "dev"
Requires-Dist: scikit-learn
Requires-Dist: sphinx ; extra == "dev"
Requires-Dist: sphinx-automodapi ; extra == "dev"
Requires-Dist: sphinx-copybutton ; extra == "dev"
Requires-Dist: sphinx-rtd-dark-mode ; extra == "dev"
Requires-Dist: sphinx_rtd_theme ; extra == "dev"
Requires-Dist: tensorboard
Requires-Dist: torch
Requires-Dist: typeguard (<3.0.0)
Project-URL: Documentation, https://github.com/paninski-lab/lightning-action
Project-URL: Repository, https://github.com/paninski-lab/lightning-action
